chain-norm/__init__.py
chain-norm/data.py
cnorm/__init__.py
cnorm/chain.py
cnorm/data.py
cnorm/rule.py
chain_norm-0.0.15.dist-info/LICENSE
chain_norm-0.0.15.dist-info/METADATA
chain_norm-0.0.15.dist-info/WHEEL
chain_norm-0.0.15.dist-info/top_level.txt
chain_norm-0.0.15.dist-info/RECORD
