Metadata-Version: 2.1
Name: chain-norm
Version: 0.0.15
Summary: chain-norm is python library for suquential text normalization
Home-page: https://github.com/roy29fuku/chain-norm
Author: Ryota Yamada
Author-email: roy29fuku@gmail.com
License: UNKNOWN
Platform: UNKNOWN
Classifier: Programming Language :: Python :: 3
Classifier: Programming Language :: Python :: 3.8
Classifier: License :: OSI Approved :: MIT License
Classifier: Operating System :: MacOS
Requires-Python: >=3.8
License-File: LICENSE
Requires-Dist: jaconv
Requires-Dist: jupyter
Requires-Dist: pip-chill
Requires-Dist: pipdeptree
Requires-Dist: twine
Requires-Dist: word2number
